GodRandom/__init__.py
GodRandom/main.py
GodRandom-0.1.dist-info/METADATA
GodRandom-0.1.dist-info/WHEEL
GodRandom-0.1.dist-info/top_level.txt
GodRandom-0.1.dist-info/RECORD
